http_fallback_storage.py
django_http_fallback_storage-1.6.dist-info/DESCRIPTION.rst
django_http_fallback_storage-1.6.dist-info/METADATA
django_http_fallback_storage-1.6.dist-info/RECORD
django_http_fallback_storage-1.6.dist-info/WHEEL
django_http_fallback_storage-1.6.dist-info/metadata.json
django_http_fallback_storage-1.6.dist-info/top_level.txt
